amplfi/__init__.py
amplfi/amplfi_init.py
amplfi/data/__init__.py
amplfi/data/base.py
amplfi/data/paths.py
amplfi/data/tasks.py
amplfi/train/__init__.py
amplfi/train/augmentations.py
amplfi/train/conversion.py
amplfi/train/losses.py
amplfi/train/prior.py
amplfi/train/architectures/__init__.py
amplfi/train/architectures/flows.py
amplfi/train/architectures/embeddings/__init__.py
amplfi/train/architectures/embeddings/base.py
amplfi/train/architectures/embeddings/dense.py
amplfi/train/architectures/embeddings/multimodal.py
amplfi/train/architectures/embeddings/resnet.py
amplfi/train/architectures/embeddings/similarity.py
amplfi/train/callbacks/__init__.py
amplfi/train/callbacks/testing.py
amplfi/train/callbacks/training.py
amplfi/train/cli/__init__.py
amplfi/train/cli/base.py
amplfi/train/cli/flow.py
amplfi/train/cli/similarity.py
amplfi/train/data/augmentors.py
amplfi/train/data/datasets/__init__.py
amplfi/train/data/datasets/base.py
amplfi/train/data/datasets/flow.py
amplfi/train/data/datasets/similarity.py
amplfi/train/data/datasets/testing.py
amplfi/train/data/utils/fs.py
amplfi/train/data/utils/utils.py
amplfi/train/data/waveforms/loader.py
amplfi/train/data/waveforms/sampler.py
amplfi/train/data/waveforms/generator/cbc.py
amplfi/train/data/waveforms/generator/generator.py
amplfi/train/data/waveforms/generator/sg.py
amplfi/train/models/__init__.py
amplfi/train/models/base.py
amplfi/train/models/flow.py
amplfi/train/models/similarity.py
amplfi/utils/__init__.py
amplfi/utils/distance.py
amplfi/utils/result.py
amplfi/utils/skymap.py
amplfi-0.5.6.dist-info/licenses/LICENSE
docs/conf.py
tests/conftest.py
tests/train/test_losses.py
tests/train/architectures/test_flows.py
tests/train/architectures/embeddings/test_embeddings.py
tests/train/cli/test_flow.py
tests/utils/test_skymap.py
amplfi-0.5.6.dist-info/METADATA
amplfi-0.5.6.dist-info/WHEEL
amplfi-0.5.6.dist-info/entry_points.txt
amplfi-0.5.6.dist-info/top_level.txt
amplfi-0.5.6.dist-info/RECORD
