Metadata-Version: 2.4
Name: amplfi
Version: 0.5.6
Summary: Accelerated Multi-messenger PE with Likelihood Free Inference
Author: Ethan Marx, Deep Chatterjee
Requires-Python: <3.13,>=3.10
License-File: LICENSE
Requires-Dist: lightray>=0.2.4
Requires-Dist: numpy<2.0.0
Requires-Dist: ml4gw>=0.7.8
Requires-Dist: lightning>=2.5.0
Requires-Dist: h5py<4,>=3.10.0
Requires-Dist: ray[default,tune]<3,>=2.38.0
Requires-Dist: bilby<3,>=2.2.3
Requires-Dist: healpy<2,>=1.16.6
Requires-Dist: jsonargparse[signatures]<5,>=4.27.1
Requires-Dist: urllib3<1.27,>=1.25.4
Requires-Dist: omegaconf<3,>=2.3.0
Requires-Dist: gwpy>=3.0.12
Requires-Dist: wandb<0.19,>=0.18.5
Requires-Dist: torch>=2.5.0
Requires-Dist: pytorch-tcn
Requires-Dist: s3fs<2025,>=2024.12.0
Requires-Dist: ligo-skymap>=2.2.2
Requires-Dist: zuko>=1.4.0
Requires-Dist: pandas[hdf5]>=2.3.1
Dynamic: license-file
